{
  "users": {
    "1379729539": {
      "coin": 1000000000,
      "joined": true,
      "refCount": 0,
      "lastClaim": 0,
      "isBanned": false,
      "username": "ARIFOFFICIAL11",
      "joinedAt": 1783789952280,
      "history": [],
      "bonusClaimed": true
    },
    "1663207738": {
      "coin": 1000000000,
      "joined": true,
      "refCount": 0,
      "lastClaim": 0,
      "isBanned": false,
      "username": "LekzoMarketV22",
      "joinedAt": 1784036602397,
      "history": [],
      "bonusClaimed": true
    },
    "8627564165": {
      "coin": 1000000000,
      "joined": true,
      "refCount": 0,
      "lastClaim": 0,
      "isBanned": false,
      "username": "rakxst",
      "joinedAt": 1783754934654,
      "history": [],
      "bonusClaimed": true
    },
    "8389860062": {
      "coin": 1000000000,
      "joined": true,
      "refCount": 0,
      "lastClaim": 0,
      "isBanned": false,
      "username": "Official_Monzo_Support_Bankingfi",
      "joinedAt": 1783756244688,
      "history": [],
      "bonusClaimed": true
    },
    "8815980013": {
      "coin": 1000000000,
      "joined": true,
      "refCount": 0,
      "lastClaim": 0,
      "isBanned": false,
      "username": "asemllue",
      "joinedAt": 1783756957422,
      "history": [],
      "bonusClaimed": true
    },
    "8728798273": {
      "coin": 1000000000,
      "joined": true,
      "refCount": 0,
      "lastClaim": 0,
      "isBanned": false,
      "username": "Revolut_Official_Supportg32",
      "joinedAt": 1783759303389,
      "history": [],
      "bonusClaimed": true
    },
    "5298780622": {
      "coin": 1000000000,
      "joined": true,
      "refCount": 0,
      "lastClaim": 0,
      "isBanned": false,
      "username": "maklomskin",
      "joinedAt": 1783796829359,
      "history": [],
      "bonusClaimed": true
    },
    "8227633855": {
      "coin": 768712510,
      "joined": true,
      "refCount": 0,
      "lastClaim": 0,
      "isBanned": false,
      "username": "dil_cu",
      "joinedAt": 1783840037300,
      "history": [],
      "bonusClaimed": true
    },
    "8456195348": {
      "coin": 1000000000,
      "joined": true,
      "refCount": 0,
      "lastClaim": 0,
      "isBanned": false,
      "username": "MUZOFFICIALREAL",
      "joinedAt": 1783872449518,
      "history": [],
      "bonusClaimed": true
    },
    "8252677222": {
      "coin": 944517451,
      "joined": true,
      "refCount": 0,
      "lastClaim": 1784001204800,
      "isBanned": false,
      "username": "KenzOfcl",
      "joinedAt": 1783874104670,
      "history": [],
      "bonusClaimed": true
    },
    "8743236358": {
      "coin": 1000000000,
      "joined": true,
      "refCount": 0,
      "lastClaim": 0,
      "isBanned": false,
      "username": "Noxx4Malas",
      "joinedAt": 1783875381207,
      "history": [],
      "bonusClaimed": true
    },
    "8477166862": {
      "coin": 1000000000,
      "joined": true,
      "refCount": 0,
      "lastClaim": 0,
      "isBanned": false,
      "username": "Rixxzzgnteng",
      "joinedAt": 1783886646244,
      "history": [],
      "bonusClaimed": true
    },
    "8224836781": {
      "coin": 722041887,
      "joined": true,
      "refCount": 0,
      "lastClaim": 0,
      "isBanned": false,
      "username": "CoinMarketCap_Official_Service69",
      "joinedAt": 1783909159940,
      "history": [],
      "bonusClaimed": true
    },
    "6816095235": {
      "coin": 1000000000,
      "joined": true,
      "refCount": 0,
      "lastClaim": 0,
      "isBanned": false,
      "username": "masganzi",
      "joinedAt": 1783939660240,
      "history": [],
      "bonusClaimed": true
    },
    "8512630850": {
      "coin": 1000000000,
      "joined": true,
      "refCount": 0,
      "lastClaim": 0,
      "isBanned": false,
      "username": "SinzyXynz",
      "joinedAt": 1783958795550,
      "history": [],
      "bonusClaimed": true
    },
    "8516898778": {
      "coin": 1000000000,
      "joined": true,
      "refCount": 0,
      "lastClaim": 0,
      "isBanned": false,
      "username": "rizkyystoree1",
      "joinedAt": 1783959411337,
      "history": [],
      "bonusClaimed": true
    },
    "8306784373": {
      "coin": 1000000000,
      "joined": true,
      "refCount": 0,
      "lastClaim": 0,
      "isBanned": false,
      "username": "yanxz_emptiness",
      "joinedAt": 1784021214089,
      "history": [],
      "bonusClaimed": true
    },
    "8223891242": {
      "coin": 1000001000,
      "joined": true,
      "refCount": 0,
      "lastClaim": 1784048973340,
      "isBanned": false,
      "username": "VxzzReal",
      "joinedAt": 1784046400309,
      "history": [],
      "bonusClaimed": true,
      "sharePremiumExpiry": 1784913330988
    },
    "8057599316": {
      "coin": 1000000000,
      "joined": true,
      "refCount": 0,
      "lastClaim": 0,
      "isBanned": false,
      "username": "gwkenzz1",
      "joinedAt": 1784108774960,
      "history": [],
      "bonusClaimed": true,
      "missions": {}
    },
    "8091007358": {
      "coin": 1000000000,
      "joined": true,
      "refCount": 0,
      "lastClaim": 0,
      "isBanned": false,
      "username": "AssasinCruel",
      "joinedAt": 1784111733832,
      "history": [],
      "bonusClaimed": true
    },
    "8240543049": {
      "coin": 1000000000,
      "joined": true,
      "refCount": 0,
      "lastClaim": 0,
      "isBanned": false,
      "username": "unzzstecu",
      "joinedAt": 1784114405259,
      "history": [],
      "bonusClaimed": true
    },
    "8084970402": {
      "coin": 1000000000,
      "joined": true,
      "refCount": 0,
      "lastClaim": 0,
      "isBanned": false,
      "username": "",
      "joinedAt": 1784125418566,
      "history": [],
      "bonusClaimed": true
    },
    "7074160743": {
      "coin": 1000000000,
      "joined": true,
      "refCount": 0,
      "lastClaim": 0,
      "isBanned": false,
      "username": "Yanzz779",
      "joinedAt": 1784153368903,
      "history": [],
      "bonusClaimed": true
    },
    "8685290981": {
      "coin": 1000000000,
      "joined": true,
      "refCount": 0,
      "lastClaim": 0,
      "isBanned": false,
      "username": "Exinnn13",
      "joinedAt": 1784153510969,
      "history": [],
      "bonusClaimed": true
    },
    "7452368268": {
      "coin": 1005230626,
      "joined": true,
      "refCount": 0,
      "lastClaim": 0,
      "isBanned": false,
      "username": "devzxbl",
      "joinedAt": 1784168829819,
      "history": [],
      "bonusClaimed": true
    },
    "6163304242": {
      "coin": 1000000000,
      "joined": true,
      "refCount": 0,
      "lastClaim": 0,
      "isBanned": false,
      "username": "DITZZ_OFFICIALMD",
      "joinedAt": 1784198626802,
      "history": [],
      "bonusClaimed": true
    },
    "8352128711": {
      "coin": 1000000000,
      "joined": true,
      "refCount": 0,
      "lastClaim": 0,
      "isBanned": false,
      "username": "mizzcrash",
      "joinedAt": 1784201714563,
      "history": [],
      "bonusClaimed": true
    },
    "8719472321": {
      "coin": 1000000000,
      "joined": true,
      "refCount": 0,
      "lastClaim": 0,
      "isBanned": false,
      "username": "Jackcytrus",
      "joinedAt": 1784205283213,
      "history": [],
      "bonusClaimed": true
    },
    "8638473165": {
      "coin": 999999900,
      "joined": true,
      "refCount": 0,
      "lastClaim": 1784287464484,
      "isBanned": false,
      "username": "Rinnnnky",
      "joinedAt": 1784287392240,
      "history": [],
      "bonusClaimed": true
    },
    "7665664073": {
      "coin": 1000000000,
      "joined": true,
      "refCount": 0,
      "lastClaim": 0,
      "isBanned": false,
      "username": "NAUFALLstore",
      "joinedAt": 1784295872214,
      "history": [],
      "bonusClaimed": true
    },
    "8699409011": {
      "coin": 1000000000,
      "joined": true,
      "refCount": 0,
      "lastClaim": 0,
      "isBanned": false,
      "username": "CoinMarketCap_Official39",
      "joinedAt": 1784296681986,
      "history": [],
      "bonusClaimed": true
    },
    "7775351050": {
      "coin": 1000000000,
      "joined": true,
      "refCount": 0,
      "lastClaim": 0,
      "isBanned": false,
      "username": "kelzzz67",
      "joinedAt": 1784418290783,
      "history": [],
      "bonusClaimed": true
    }
  },
  "scripts": [],
  "redeemCodes": {},
  "maintenanceMode": false,
  "groups": {
    "-1003974057755": {
      "chatId": "-1003974057755",
      "title": "1KG 1ONS (OON)",
      "addedBy": "8223891242",
      "addedAt": 1784049215729,
      "active": true
    },
    "-1004315045187": {
      "chatId": "-1004315045187",
      "title": "GRUP GABUTAN",
      "addedBy": "8223891242",
      "addedAt": 1784049240771,
      "active": true
    },
    "-1003548899649": {
      "chatId": "-1003548899649",
      "title": "𝐆𝐁 𝐉𝐎𝐊𝐈 𝐒𝐏𝐀𝐂𝐄𝐌𝐀𝐍 𝐁𝐘 𝐁𝐀𝐋𝐙",
      "addedBy": "8223891242",
      "addedAt": 1784049268421,
      "active": true
    },
    "-1003894478155": {
      "chatId": "-1003894478155",
      "title": "𝐆𝐫𝐮𝐩 𝐊𝐡𝐮𝐬𝐮𝐬 𝐌𝐮𝐬𝐢𝐤 𝐕𝐓𝐗",
      "addedBy": "8223891242",
      "addedAt": 1784049306034,
      "active": true
    },
    "-1003640980248": {
      "chatId": "-1003640980248",
      "title": "fixwin zkaa",
      "addedBy": "8223891242",
      "addedAt": 1784049330987,
      "active": true
    }
  },
  "noktelData": {
    "hadiah": {},
    "userLimits": {
      "8252677222": 2,
      "8477166862": 1,
      "8223891242": 0,
      "7452368268": 1
    }
  },
  "nokosData": {
    "hadiah": {},
    "userLimits": {
      "8227633855": 0,
      "8252677222": 0,
      "8477166862": 1,
      "8516898778": 1,
      "8223891242": 1,
      "7665664073": 2
    }
  },
  "tradingData": {
    "harga": {
      "BTC": 56764204,
      "ETH": 208818823,
      "SOL": 80045
    },
    "userSlots": {
      "8227633855": {
        "BTC": 3,
        "ETH": 3,
        "SOL": 4
      },
      "8252677222": {
        "BTC": 0,
        "ETH": 1,
        "SOL": 0
      },
      "7452368268": {
        "BTC": 0,
        "ETH": 0,
        "SOL": 0
      },
      "8224836781": {
        "BTC": 0,
        "ETH": 1,
        "SOL": 1
      },
      "8638473165": {
        "BTC": 0,
        "ETH": 0,
        "SOL": 0
      }
    },
    "lastUpdate": 1784418136145
  },
  "jualSCData": {
    "submissions": {},
    "pending": {}
  },
  "shopBulk": {},
  "whitelist": [
    8616365298
  ]
}